cognite_function_apps/__init__.py
cognite_function_apps/_version.py
cognite_function_apps/app.py
cognite_function_apps/base_client.py
cognite_function_apps/cli.py
cognite_function_apps/client.py
cognite_function_apps/client_generation.py
cognite_function_apps/convert.py
cognite_function_apps/dependency_registry.py
cognite_function_apps/formatting.py
cognite_function_apps/introspection.py
cognite_function_apps/logger.py
cognite_function_apps/mcp.py
cognite_function_apps/models.py
cognite_function_apps/py.typed
cognite_function_apps/routing.py
cognite_function_apps/schema.py
cognite_function_apps/service.py
cognite_function_apps/tracer.py
cognite_function_apps/devserver/__init__.py
cognite_function_apps/devserver/asgi.py
cognite_function_apps/devserver/auth.py
cognite_function_apps/devserver/swagger.py
cognite_function_apps/templates/__init__.py
cognite_function_apps/templates/client_template.jinja2
cognite_function_apps-0.6.1.dist-info/METADATA
cognite_function_apps-0.6.1.dist-info/WHEEL
cognite_function_apps-0.6.1.dist-info/entry_points.txt
cognite_function_apps-0.6.1.dist-info/licenses/LICENSE
cognite_function_apps-0.6.1.dist-info/RECORD
